plainhtml/__init__.py
plainhtml/core.py
plainhtml/parser.py
plainhtml/utils.py
plainhtml-0.2.2.dist-info/LICENSE
plainhtml-0.2.2.dist-info/METADATA
plainhtml-0.2.2.dist-info/WHEEL
plainhtml-0.2.2.dist-info/RECORD
