Metadata-Version: 2.1
Name: plainhtml
Version: 0.2.2
Summary: Extract plain text from HTML
Author: Severin Simmler
Author-email: s.simmler@snapaddy.com
Requires-Python: >=3.10,<4.0
Classifier: Programming Language :: Python :: 3
Classifier: Programming Language :: Python :: 3.10
Classifier: Programming Language :: Python :: 3.11
Classifier: Programming Language :: Python :: 3.12
Requires-Dist: lxml[html-clean] (>=5.1.0,<6.0.0)
